zscore_anomaly/__init__.py
zscore_anomaly/zscore_anomaly_detector.py
zscore_anomaly_detector-0.4.dist-info/METADATA
zscore_anomaly_detector-0.4.dist-info/WHEEL
zscore_anomaly_detector-0.4.dist-info/top_level.txt
zscore_anomaly_detector-0.4.dist-info/RECORD
