Metadata-Version: 2.1
Name: zscore_anomaly_detector
Version: 0.4
Summary: A Python package to detect anomalies using Z-Scores
Home-page: 
Author: Volkan OBAN
Author-email: volkanobn@gmail.com
Classifier: Programming Language :: Python :: 3
Classifier: License :: OSI Approved :: MIT License
Classifier: Operating System :: OS Independent
Requires-Python: >=3.6
Requires-Dist: numpy
Requires-Dist: pandas
